fastapi_rss/__init__.py
fastapi_rss/models/__init__.py
fastapi_rss/models/category.py
fastapi_rss/models/cloud.py
fastapi_rss/models/enclosure.py
fastapi_rss/models/feed.py
fastapi_rss/models/guid.py
fastapi_rss/models/image.py
fastapi_rss/models/item.py
fastapi_rss/models/itunes.py
fastapi_rss/models/source.py
fastapi_rss/models/textinput.py
fastapi_rss/rss_response.py
fastapi_rss/utils.py
fastapi_rss-0.4.0.dist-info/AUTHORS.md
fastapi_rss-0.4.0.dist-info/LICENSE
fastapi_rss-0.4.0.dist-info/METADATA
fastapi_rss-0.4.0.dist-info/WHEEL
fastapi_rss-0.4.0.dist-info/RECORD
